filemint/__init__.py
filemint/cli.py
filemint/generators.py
filemint-0.1.0.dist-info/licenses/LICENSE
tests/__init__.py
tests/test_generators.py
filemint-0.1.0.dist-info/METADATA
filemint-0.1.0.dist-info/WHEEL
filemint-0.1.0.dist-info/entry_points.txt
filemint-0.1.0.dist-info/top_level.txt
filemint-0.1.0.dist-info/RECORD
